{
  "theme": "hope",
  "verses": [
    {
      "vers": "Ty jag vet vilka tankar jag har för er, säger HERREN, nämligen fridens tankar och inte ofärdens, för att ge er en framtid och ett hopp.",
      "referens": "Jeremia 29:11"
    },
    {
      "vers": "Men de som hoppas på HERREN får ny kraft, de får nya vingars lyftning. De springer utan att bli trötta, de går utan att bli utmattade.",
      "referens": "Jesaja 40:31"
    },
    {
      "vers": "Må hoppets Gud uppfylla er med all glädje och frid i tron, så att ni överflödar av hopp genom den helige Andes kraft.",
      "referens": "Romarbrevet 15:13"
    },
    {
      "vers": "Och hoppet gör inte besviken, ty Guds kärlek är utgjuten i våra hjärtan genom den helige Ande som har blivit oss given.",
      "referens": "Romarbrevet 5:5"
    },
    {
      "vers": "Välsignad är den man som förtröstar på HERREN och som har HERREN till sitt hopp.",
      "referens": "Jeremia 17:7"
    },
    {
      "vers": "Varför är du så nedstämd, min själ, varför oroar du dig inom mig? Hoppas på Gud, ty jag ska ännu få prisa honom, min frälsning och min Gud.",
      "referens": "Psaltaren 42:12"
    }
  ],
  "count": 6,
  "lastUpdated": "2025-12-01T21:39:53.747Z"
}